[
  {
    "gameLink": "",
    "homeTeam": "Âncora-Praia Fc",
    "stadium": "Campo Paulino Velho Gomes",
    "awayTeam": "Perspectiva Em Jogo Ad \"A\"",
    "date": "5 nov",
    "hour": "10:00",
    "score": " - - -"
  },
  {
    "gameLink": "",
    "homeTeam": "Neves Fc \"A\"",
    "stadium": "Campo Alferes Pinto Ribeiro - N.º 2",
    "awayTeam": "Cc \"Os Torreenses\"",
    "date": "5 nov",
    "hour": "10:00",
    "score": " - - -"
  },
  {
    "gameLink": "",
    "homeTeam": "Cd Cerveira",
    "stadium": "Estádio Municipal Rafael Pedreira",
    "awayTeam": "Sc Vianense \"B\"",
    "date": "5 nov",
    "hour": "10:00",
    "score": " - - -"
  },
  {
    "gameLink": "",
    "homeTeam": "Ad \"Os Limianos\" \"A\"",
    "stadium": "Campo Cruzeiro",
    "awayTeam": "Adc Correlhã",
    "date": "5 nov",
    "hour": "10:00",
    "score": " - - -"
  },
  {
    "gameLink": "",
    "homeTeam": "Torre Sc",
    "stadium": "Campo Das Monções",
    "awayTeam": "Arc Guilhadeses",
    "date": "5 nov",
    "hour": "10:00",
    "score": " - - -"
  },
  {
    "gameLink": "",
    "homeTeam": "Ud Moreira \"A\"",
    "stadium": "Campo Tomada",
    "awayTeam": "Ad Barroselas \"B\"",
    "date": "5 nov",
    "hour": "10:00",
    "score": " - - -"
  }
]